cosaccess
